setup.py
kinesisutils/__init__.py
kinesisutils/kinesisutils.py
kinesisutils.egg-info/PKG-INFO
kinesisutils.egg-info/SOURCES.txt
kinesisutils.egg-info/dependency_links.txt
kinesisutils.egg-info/requires.txt
kinesisutils.egg-info/top_level.txt