Metadata-Version: 1.1
Name: kinesisutils
Version: 0.0.3
Summary: Kinesis utilities
Home-page: https://github.com/findhotel/kinesisutils
Author: German Gomez-Herrero
Author-email: german@findhotel.net
License: MIT
Platform: UNKNOWN
Classifier: Programming Language :: Python :: 3
